{"cameraMode":{"drawMode":0,"name":"Shaded","section":"Shading Mode"},"sceneLighting":false,"audioPlay":false,"sceneViewState":{"m_AlwaysRefresh":false,"showFog":true,"showSkybox":false,"showFlares":true,"showImageEffects":true,"showParticleSystems":true,"showVisualEffectGraphs":true,"m_FxEnabled":true},"in2DMode":false,"pivot":{"x":-0.00241813063621521,"y":0.12496346235275269,"z":0.0038491487503051759},"rotation":{"x":0.28703925013542178,"y":-0.4657689332962036,"z":0.162827268242836,"w":0.821071445941925},"size":0.8660253882408142,"orthographic":false}